hkg_cli/__init__.py
hkg_cli/components/__init__.py
hkg_cli/components/api_connector/__init__.py
hkg_cli/components/api_connector/core.py
hkg_cli/components/api_connector/models.py
hkg_cli/components/base.py
hkg_cli/components/data_harvesting/__init__.py
hkg_cli/components/data_harvesting/core.py
hkg_cli/components/data_harvesting/models.py
hkg_cli/components/data_pipeline/__init__.py
hkg_cli/components/data_pipeline/core.py
hkg_cli/components/data_pipeline/models.py
hkg_cli/components/data_storage_api/__init__.py
hkg_cli/components/data_storage_api/core.py
hkg_cli/components/data_storage_api/models.py
hkg_cli/components/data_storage_api_manifests/__init__.py
hkg_cli/components/data_storage_api_manifests/core.py
hkg_cli/components/data_storage_api_manifests/models.py
hkg_cli/components/documentation/__init__.py
hkg_cli/components/documentation/core.py
hkg_cli/components/documentation/models.py
hkg_cli/components/documentation_manifests/__init__.py
hkg_cli/components/documentation_manifests/core.py
hkg_cli/components/documentation_manifests/models.py
hkg_cli/components/internal_data_model/__init__.py
hkg_cli/components/internal_data_model/core.py
hkg_cli/components/internal_data_model/models.py
hkg_cli/components/manager.py
hkg_cli/components/mapping/__init__.py
hkg_cli/components/mapping/core.py
hkg_cli/components/mapping/models.py
hkg_cli/components/models.py
hkg_cli/components/ui/.gitkeep
hkg_cli/docker/__init__.py
hkg_cli/docker/commands.py
hkg_cli/git/__init__.py
hkg_cli/git/commands.py
hkg_cli/git/models.py
hkg_cli/main.py
hkg_cli/subcommands/__init__.py
hkg_cli/subcommands/setup.py
hkg_cli/subcommands/utils.py
hkg_cli-0.1.0.dist-info/AUTHORS.md
hkg_cli-0.1.0.dist-info/LICENSE
hkg_cli-0.1.0.dist-info/LICENSES/CC0-1.0.txt
hkg_cli-0.1.0.dist-info/LICENSES/MIT.txt
hkg_cli-0.1.0.dist-info/METADATA
hkg_cli-0.1.0.dist-info/WHEEL
hkg_cli-0.1.0.dist-info/entry_points.txt
hkg_cli-0.1.0.dist-info/RECORD
