Metadata-Version: 2.3
Name: hkg-cli
Version: 0.1.0
Summary: CLI app to set up micro services of Helmholtz Knowledge Graph locally
License: MIT
Keywords: typer,hkg,cli
Author: Mustafa Soylu
Author-email: m.soylu@fz-juelich.de
Maintainer: Mustafa Soylu
Maintainer-email: m.soylu@fz-juelich.de
Requires-Python: >=3.9,<4.0
Classifier: Intended Audience :: Developers
Classifier: Intended Audience :: Science/Research
Classifier: License :: OSI Approved :: MIT License
Classifier: Operating System :: POSIX :: Linux
Classifier: Programming Language :: Python :: 3
Classifier: Programming Language :: Python :: 3.9
Classifier: Programming Language :: Python :: 3.10
Classifier: Programming Language :: Python :: 3.11
Classifier: Programming Language :: Python :: 3.12
Classifier: Programming Language :: Python :: 3.13
Requires-Dist: importlib (>=1.0.4,<2.0.0)
Requires-Dist: importlib-metadata (>=8.5.0,<9.0.0)
Requires-Dist: pydantic (>=2.10.3,<3.0.0)
Requires-Dist: pyyaml (>=6.0.2,<7.0.0)
Requires-Dist: tomlkit (>=0.13.2,<0.14.0)
Requires-Dist: typer (>=0.14.0,<0.15.0)
Requires-Dist: wrapt (>=1.17.0,<2.0.0)
Project-URL: Documentation, https://hmc.pages.hzdr.de/hmc-public/unhide/development/hkg-cli
Project-URL: Homepage, https://hmc.pages.hzdr.de/hmc-public/unhide/development/hkg-cli
Project-URL: Repository, https://codebase.helmholtz.cloud/hmc/hmc-public/unhide/development/hkg-cli.git
